roman_numerals_converter/__init__.py
roman_numerals_converter/__main__.py
roman_numerals_converter/py.typed
roman_numerals_converter/roman.py
roman_numerals_converter-0.2.1.dist-info/LICENSE
roman_numerals_converter-0.2.1.dist-info/METADATA
roman_numerals_converter-0.2.1.dist-info/WHEEL
roman_numerals_converter-0.2.1.dist-info/entry_points.txt
roman_numerals_converter-0.2.1.dist-info/RECORD
