Metadata-Version: 2.1
Name: roman-numerals-converter
Version: 0.2.1
Summary: 
Author: ceddicedced
Author-email: cedric@busacker.dev
Requires-Python: >=3.10,<4.0
Classifier: Programming Language :: Python :: 3
Classifier: Programming Language :: Python :: 3.10
Classifier: Programming Language :: Python :: 3.11
Classifier: Programming Language :: Python :: 3.12
Requires-Dist: click (>=8.1.7,<9.0.0)
Requires-Dist: pre-commit (>=3.5.0,<4.0.0)
Requires-Dist: ruff (>=0.1.6,<0.2.0)
